mmllib/__init__.py
mmllib/cmds.py
mmllib/esp.py
mmllib/mml.py
mmllib/musicxml.py
mmllib/nxc.py
mmllib/parser.py
mmllib/playlist.py
MMLlib-1.4.dist-info/LICENCE
MMLlib-1.4.dist-info/METADATA
MMLlib-1.4.dist-info/WHEEL
MMLlib-1.4.dist-info/entry_points.txt
MMLlib-1.4.dist-info/top_level.txt
MMLlib-1.4.dist-info/RECORD
