Metadata-Version: 2.1
Name: MMLlib
Version: 1.4
Summary: Modern library for handling Music Macro Language
Home-page: https://edugit.org/nik/mmllib
Maintainer: Dominik George
Maintainer-email: nik@naturalnet.de
License: MirOS
Platform: UNKNOWN
Classifier: Development Status :: 5 - Production/Stable
Classifier: Environment :: Console
Classifier: Intended Audience :: Developers
Classifier: Intended Audience :: Science/Research
Classifier: License :: OSI Approved
Classifier: Operating System :: OS Independent
Classifier: Programming Language :: Python
Classifier: Topic :: Artistic Software
Classifier: Topic :: Multimedia :: Sound/Audio :: Conversion
Classifier: Topic :: Software Development :: Libraries :: Python Modules
License-File: LICENCE
